django_pg_returning/__init__.py
django_pg_returning/compatibility.py
django_pg_returning/manager.py
django_pg_returning/models.py
django_pg_returning/queryset.py
django_pg_returning-2.0.2.dist-info/LICENSE
django_pg_returning-2.0.2.dist-info/METADATA
django_pg_returning-2.0.2.dist-info/WHEEL
django_pg_returning-2.0.2.dist-info/top_level.txt
django_pg_returning-2.0.2.dist-info/RECORD
