Metadata-Version: 2.1
Name: django-pg-returning
Version: 2.0.2
Summary: A small library implementing PostgreSQL ability to return rows in DML statements for Django
Home-page: https://github.com/M1hacka/django-pg-returning
Author: Mikhail Shvein
Author-email: work_shvein_mihail@mail.ru
License: BSD 3-clause "New" or "Revised" License
License-File: LICENSE
Requires-Dist: django >=1.7
Requires-Dist: typing ; python_version < "3.5"
